PythonOpencv3XShiliChuyiFix1/README.md
PythonOpencv3XShiliChuyiFix1/__init__.py
PythonOpencv3XShiliChuyiFix1/__main__.py
PythonOpencv3XShiliChuyiFix1/file.epub
PythonOpencv3XShiliChuyiFix1/index.html
PythonOpencv3XShiliChuyiFix1/css/__init__.py
PythonOpencv3XShiliChuyiFix1/css/annotations.css
PythonOpencv3XShiliChuyiFix1/css/main.css
PythonOpencv3XShiliChuyiFix1/css/normalize.css
PythonOpencv3XShiliChuyiFix1/css/popup.css
PythonOpencv3XShiliChuyiFix1/font/__init__.py
PythonOpencv3XShiliChuyiFix1/font/fontello.eot
PythonOpencv3XShiliChuyiFix1/font/fontello.svg
PythonOpencv3XShiliChuyiFix1/font/fontello.ttf
PythonOpencv3XShiliChuyiFix1/font/fontello.woff
PythonOpencv3XShiliChuyiFix1/img/__init__.py
PythonOpencv3XShiliChuyiFix1/img/annotator-glyph-sprite.png
PythonOpencv3XShiliChuyiFix1/img/annotator-icon-sprite.png
PythonOpencv3XShiliChuyiFix1/img/apple-touch-icon.png
PythonOpencv3XShiliChuyiFix1/img/cancelfullscreen.png
PythonOpencv3XShiliChuyiFix1/img/close.png
PythonOpencv3XShiliChuyiFix1/img/fullscreen.png
PythonOpencv3XShiliChuyiFix1/img/loader.gif
PythonOpencv3XShiliChuyiFix1/img/menu-icon.png
PythonOpencv3XShiliChuyiFix1/img/save.png
PythonOpencv3XShiliChuyiFix1/img/saved.png
PythonOpencv3XShiliChuyiFix1/img/settings-s.png
PythonOpencv3XShiliChuyiFix1/img/settings.png
PythonOpencv3XShiliChuyiFix1/img/star.png
PythonOpencv3XShiliChuyiFix1/js/__init__.py
PythonOpencv3XShiliChuyiFix1/js/epub.js
PythonOpencv3XShiliChuyiFix1/js/epub.min.js
PythonOpencv3XShiliChuyiFix1/js/epub.min.map
PythonOpencv3XShiliChuyiFix1/js/hooks.min.js
PythonOpencv3XShiliChuyiFix1/js/hooks.min.map
PythonOpencv3XShiliChuyiFix1/js/reader.js
PythonOpencv3XShiliChuyiFix1/js/reader.js.map
PythonOpencv3XShiliChuyiFix1/js/reader.min.js
PythonOpencv3XShiliChuyiFix1/js/reader.min.map
PythonOpencv3XShiliChuyiFix1/js/hooks/__init__.py
PythonOpencv3XShiliChuyiFix1/js/hooks/extensions/__init__.py
PythonOpencv3XShiliChuyiFix1/js/hooks/extensions/highlight.js
python_opencv_3_x_shili_chuyi_fix1-2025.3.25.1.dist-info/METADATA
python_opencv_3_x_shili_chuyi_fix1-2025.3.25.1.dist-info/WHEEL
python_opencv_3_x_shili_chuyi_fix1-2025.3.25.1.dist-info/entry_points.txt
python_opencv_3_x_shili_chuyi_fix1-2025.3.25.1.dist-info/top_level.txt
python_opencv_3_x_shili_chuyi_fix1-2025.3.25.1.dist-info/RECORD
